{
  "type": "workflow_collections",
  "data": [
    {
      "uuid": "3586dab8-5e82-4b17-ab27-aa236138a1ef",
      "@type": "WorkflowCollection",
      "workflows": [
        {
          "@type": "Workflow",
          "uuid": "80a55505-d9a2-4774-b1dd-112c26e03e86",
          "collection": "/api/3/workflow_collections/3586dab8-5e82-4b17-ab27-aa236138a1ef",
          "steps": [
            {
              "uuid": "c1e15ba5-46f5-4ba7-bc26-9111873ad13f",
              "@type": "WorkflowStep",
              "name": "Start",
              "description": null,
              "status": null,
              "arguments": {
                "step_variables": {
                  "input": {
                    "params": []
                  }
                }
              },
              "left": "20",
              "top": "20",
              "stepType": "/api/3/workflow_step_types/b348f017-9a94-471f-87f8-ce88b6a7ad62"
            },
            {
              "uuid": "a6e437a3-f107-4fa3-8ad2-e27feb356934",
              "@type": "WorkflowStep",
              "name": "Create Investigation",
              "description": null,
              "status": null,
              "arguments": {
                "name": "Taegis XDR",
                "config": "",
                "params": {
                  "description": "",
                  "key_findings": "",
                  "priority": 3,
                  "status": "Open",
                  "assignee_id": "",
                  "alerts": ""
                },
                "version": "1.2.0",
                "connector": "taegis-xdr",
                "operation": "create_investigation",
                "operationTitle": "Create Investigation"
              },
              "left": "188",
              "top": "120",
              "stepType": "/api/3/workflow_step_types/0bfed618-0316-11e7-93ae-92361f002671"
            }
          ],
          "triggerLimit": null,
          "description": "Creates investigation fields based on the descriptions of investigations and other input parameters specified.",
          "name": "Create Investigation",
          "tag": "#Taegis XDR",
          "recordTags": [
            "Taegis",
            "taegis-xdr"
          ],
          "isActive": false,
          "debug": false,
          "singleRecordExecution": false,
          "parameters": [],
          "synchronous": false,
          "triggerStep": "/api/3/workflow_steps/c1e15ba5-46f5-4ba7-bc26-9111873ad13f",
          "routes": [
            {
              "uuid": "3e596ae1-2aa4-4853-a424-9e1145819269",
              "@type": "WorkflowRoute",
              "label": null,
              "isExecuted": false,
              "name": "Start-> Create Investigation",
              "sourceStep": "/api/3/workflow_steps/c1e15ba5-46f5-4ba7-bc26-9111873ad13f",
              "targetStep": "/api/3/workflow_steps/a6e437a3-f107-4fa3-8ad2-e27feb356934"
            }
          ]
        },
        {
          "@type": "Workflow",
          "uuid": "9b15b802-5012-4f97-91c0-cd4d74cdc1aa",
          "collection": "/api/3/workflow_collections/3586dab8-5e82-4b17-ab27-aa236138a1ef",
          "steps": [
            {
              "uuid": "235db8c4-12df-4cf7-bb85-9dc69daaca4c",
              "@type": "WorkflowStep",
              "name": "Start",
              "description": null,
              "status": null,
              "arguments": {
                "step_variables": {
                  "input": {
                    "params": []
                  }
                }
              },
              "left": "20",
              "top": "20",
              "stepType": "/api/3/workflow_step_types/b348f017-9a94-471f-87f8-ce88b6a7ad62"
            },
            {
              "uuid": "dda94533-92dc-4805-8565-545c4e5b350a",
              "@type": "WorkflowStep",
              "name": "Get Investigations",
              "description": null,
              "status": null,
              "arguments": {
                "name": "Taegis XDR",
                "config": "",
                "params": {
                  "query": "",
                  "orderByField": "",
                  "orderDirection": "Ascending",
                  "page": 1,
                  "perPage": 10
                },
                "version": "1.2.0",
                "connector": "taegis-xdr",
                "operation": "get_investigations",
                "operationTitle": "Get Investigations"
              },
              "left": "188",
              "top": "120",
              "stepType": "/api/3/workflow_step_types/0bfed618-0316-11e7-93ae-92361f002671"
            }
          ],
          "triggerLimit": null,
          "description": "Retrieves a list of investigations filter asset state, CQL Query, and other input parameters specified.",
          "name": "Get Investigations",
          "tag": "#Taegis XDR",
          "recordTags": [
            "Taegis",
            "taegis-xdr"
          ],
          "isActive": false,
          "debug": false,
          "singleRecordExecution": false,
          "parameters": [],
          "synchronous": false,
          "triggerStep": "/api/3/workflow_steps/235db8c4-12df-4cf7-bb85-9dc69daaca4c",
          "routes": [
            {
              "uuid": "19df1d2d-f840-495a-a404-44b0bb47eada",
              "@type": "WorkflowRoute",
              "label": null,
              "isExecuted": false,
              "name": "Start-> Get Investigations",
              "sourceStep": "/api/3/workflow_steps/235db8c4-12df-4cf7-bb85-9dc69daaca4c",
              "targetStep": "/api/3/workflow_steps/dda94533-92dc-4805-8565-545c4e5b350a"
            }
          ]
        },
        {
          "@type": "Workflow",
          "uuid": "a22fffa5-f0c1-4689-a285-ca43a419018e",
          "collection": "/api/3/workflow_collections/3586dab8-5e82-4b17-ab27-aa236138a1ef",
          "steps": [
            {
              "uuid": "591701dc-a237-483a-8bba-cf2eb3567b83",
              "@type": "WorkflowStep",
              "name": "Start",
              "description": null,
              "status": null,
              "arguments": {
                "step_variables": {
                  "input": {
                    "params": []
                  }
                }
              },
              "left": "20",
              "top": "20",
              "stepType": "/api/3/workflow_step_types/b348f017-9a94-471f-87f8-ce88b6a7ad62"
            },
            {
              "uuid": "edc097a5-e97c-4666-9e71-37307b3e5919",
              "@type": "WorkflowStep",
              "name": "Get Investigations Alerts",
              "description": null,
              "status": null,
              "arguments": {
                "name": "Taegis XDR",
                "config": "",
                "params": {
                  "investigation_id": "",
                  "page": 1,
                  "perPage": 10
                },
                "version": "1.2.0",
                "connector": "taegis-xdr",
                "operation": "get_investigations_alerts",
                "operationTitle": "Get Investigations Alerts"
              },
              "left": "188",
              "top": "120",
              "stepType": "/api/3/workflow_step_types/0bfed618-0316-11e7-93ae-92361f002671"
            }
          ],
          "triggerLimit": null,
          "description": "Retrieves a list of alerts associated with an investigation based on the investigation ID and other input parameters specified.",
          "name": "Get Investigations Alerts",
          "tag": "#Taegis XDR",
          "recordTags": [
            "Taegis",
            "taegis-xdr"
          ],
          "isActive": false,
          "debug": false,
          "singleRecordExecution": false,
          "parameters": [],
          "synchronous": false,
          "triggerStep": "/api/3/workflow_steps/591701dc-a237-483a-8bba-cf2eb3567b83",
          "routes": [
            {
              "uuid": "b028ecb0-3ba8-40f1-98f8-d5274592ee33",
              "@type": "WorkflowRoute",
              "label": null,
              "isExecuted": false,
              "name": "Start-> Get Investigations Alerts",
              "sourceStep": "/api/3/workflow_steps/591701dc-a237-483a-8bba-cf2eb3567b83",
              "targetStep": "/api/3/workflow_steps/edc097a5-e97c-4666-9e71-37307b3e5919"
            }
          ]
        },
        {
          "@type": "Workflow",
          "uuid": "1fc846d1-4e81-4554-bd73-7b9fbe36a3e8",
          "collection": "/api/3/workflow_collections/3586dab8-5e82-4b17-ab27-aa236138a1ef",
          "steps": [
            {
              "uuid": "0170a625-e5c0-43f8-9fa5-06fa6a9923d4",
              "@type": "WorkflowStep",
              "name": "Start",
              "description": null,
              "status": null,
              "arguments": {
                "step_variables": {
                  "input": {
                    "params": []
                  }
                }
              },
              "left": "20",
              "top": "20",
              "stepType": "/api/3/workflow_step_types/b348f017-9a94-471f-87f8-ce88b6a7ad62"
            },
            {
              "uuid": "de017fa5-fbaf-421e-b1cb-b4011472e518",
              "@type": "WorkflowStep",
              "name": "Update Investigation",
              "description": null,
              "status": null,
              "arguments": {
                "name": "Taegis XDR",
                "config": "",
                "params": {
                  "investigation_id": "",
                  "description": "",
                  "key_findings": "",
                  "priority": "",
                  "status": "Active",
                  "assignee_id": ""
                },
                "version": "1.2.0",
                "connector": "taegis-xdr",
                "operation": "update_investigation",
                "operationTitle": "Update Investigation"
              },
              "left": "188",
              "top": "120",
              "stepType": "/api/3/workflow_step_types/0bfed618-0316-11e7-93ae-92361f002671"
            }
          ],
          "triggerLimit": null,
          "description": "Updates investigation fields based on the investigation ID and other input parameters specified.",
          "name": "Update Investigation",
          "tag": "#Taegis XDR",
          "recordTags": [
            "Taegis",
            "taegis-xdr"
          ],
          "isActive": false,
          "debug": false,
          "singleRecordExecution": false,
          "parameters": [],
          "synchronous": false,
          "triggerStep": "/api/3/workflow_steps/0170a625-e5c0-43f8-9fa5-06fa6a9923d4",
          "routes": [
            {
              "uuid": "60676edc-22de-487b-9617-0d58812c2dd7",
              "@type": "WorkflowRoute",
              "label": null,
              "isExecuted": false,
              "name": "Start-> Update Investigation",
              "sourceStep": "/api/3/workflow_steps/0170a625-e5c0-43f8-9fa5-06fa6a9923d4",
              "targetStep": "/api/3/workflow_steps/de017fa5-fbaf-421e-b1cb-b4011472e518"
            }
          ]
        },
        {
          "@type": "Workflow",
          "uuid": "8bc87fbd-a55e-4c49-8968-56d78d9c590c",
          "collection": "/api/3/workflow_collections/3586dab8-5e82-4b17-ab27-aa236138a1ef",
          "steps": [
            {
              "uuid": "7ec371a9-2d25-481a-94ad-e772eebcaa22",
              "@type": "WorkflowStep",
              "name": "Start",
              "description": null,
              "status": null,
              "arguments": {
                "step_variables": {
                  "input": {
                    "params": []
                  }
                }
              },
              "left": "20",
              "top": "20",
              "stepType": "/api/3/workflow_step_types/b348f017-9a94-471f-87f8-ce88b6a7ad62"
            },
            {
              "uuid": "189331ae-9b13-4d53-b253-6b3c20b9a6be",
              "@type": "WorkflowStep",
              "name": "Unarchive Investigation",
              "description": null,
              "status": null,
              "arguments": {
                "name": "Taegis XDR",
                "config": "",
                "params": {
                  "investigation_id": ""
                },
                "version": "1.2.0",
                "connector": "taegis-xdr",
                "operation": "unarchive_investigation",
                "operationTitle": "Unarchive Investigation"
              },
              "left": "188",
              "top": "120",
              "stepType": "/api/3/workflow_step_types/0bfed618-0316-11e7-93ae-92361f002671"
            }
          ],
          "triggerLimit": null,
          "description": "Unarchives investigation based on the investigation ID specified.",
          "name": "Unarchive Investigation",
          "tag": "#Taegis XDR",
          "recordTags": [
            "Taegis",
            "taegis-xdr"
          ],
          "isActive": false,
          "debug": false,
          "singleRecordExecution": false,
          "parameters": [],
          "synchronous": false,
          "triggerStep": "/api/3/workflow_steps/7ec371a9-2d25-481a-94ad-e772eebcaa22",
          "routes": [
            {
              "uuid": "dd1ff8a6-456d-4a0b-ac0e-a9267394bb8a",
              "@type": "WorkflowRoute",
              "label": null,
              "isExecuted": false,
              "name": "Start-> Unarchive Investigation",
              "sourceStep": "/api/3/workflow_steps/7ec371a9-2d25-481a-94ad-e772eebcaa22",
              "targetStep": "/api/3/workflow_steps/189331ae-9b13-4d53-b253-6b3c20b9a6be"
            }
          ]
        },
        {
          "@type": "Workflow",
          "uuid": "594a81b7-b7ad-4f27-91c4-b153edfcaf79",
          "collection": "/api/3/workflow_collections/3586dab8-5e82-4b17-ab27-aa236138a1ef",
          "steps": [
            {
              "uuid": "90e45b83-87b9-45d8-bfc8-fc9859a4420e",
              "@type": "WorkflowStep",
              "name": "Start",
              "description": null,
              "status": null,
              "arguments": {
                "step_variables": {
                  "input": {
                    "params": []
                  }
                }
              },
              "left": "20",
              "top": "20",
              "stepType": "/api/3/workflow_step_types/b348f017-9a94-471f-87f8-ce88b6a7ad62"
            },
            {
              "uuid": "2d3dcca6-63f0-4ab2-82f7-c3fb55167a25",
              "@type": "WorkflowStep",
              "name": "Add Alerts to Investigation",
              "description": null,
              "status": null,
              "arguments": {
                "name": "Taegis XDR",
                "config": "",
                "params": {
                  "investigation_id": "",
                  "alerts": ""
                },
                "version": "1.2.0",
                "connector": "taegis-xdr",
                "operation": "add_alerts_to_investigation",
                "operationTitle": "Add Alerts to Investigation"
              },
              "left": "188",
              "top": "120",
              "stepType": "/api/3/workflow_step_types/0bfed618-0316-11e7-93ae-92361f002671"
            }
          ],
          "triggerLimit": null,
          "description": "Adds Alert to an existing investigation based on the investigation ID.",
          "name": "Add Alerts to Investigation",
          "tag": "#Taegis XDR",
          "recordTags": [
            "Taegis",
            "taegis-xdr"
          ],
          "isActive": false,
          "debug": false,
          "singleRecordExecution": false,
          "parameters": [],
          "synchronous": false,
          "triggerStep": "/api/3/workflow_steps/90e45b83-87b9-45d8-bfc8-fc9859a4420e",
          "routes": [
            {
              "uuid": "c3e59873-be2c-4854-8b19-2b8d42cb0c70",
              "@type": "WorkflowRoute",
              "label": null,
              "isExecuted": false,
              "name": "Start-> Add Alerts to Investigation",
              "sourceStep": "/api/3/workflow_steps/90e45b83-87b9-45d8-bfc8-fc9859a4420e",
              "targetStep": "/api/3/workflow_steps/2d3dcca6-63f0-4ab2-82f7-c3fb55167a25"
            }
          ]
        },
        {
          "@type": "Workflow",
          "uuid": "974196e0-e58a-41d4-8d6f-7348eac18a7a",
          "collection": "/api/3/workflow_collections/3586dab8-5e82-4b17-ab27-aa236138a1ef",
          "steps": [
            {
              "uuid": "653f6283-63d6-42a8-9c2f-4bdc91599645",
              "@type": "WorkflowStep",
              "name": "Start",
              "description": null,
              "status": null,
              "arguments": {
                "step_variables": {
                  "input": {
                    "params": []
                  }
                }
              },
              "left": "20",
              "top": "20",
              "stepType": "/api/3/workflow_step_types/b348f017-9a94-471f-87f8-ce88b6a7ad62"
            },
            {
              "uuid": "775de46f-c4a7-475f-9769-bf3fa1d34177",
              "@type": "WorkflowStep",
              "name": "Add Events to Investigation",
              "description": null,
              "status": null,
              "arguments": {
                "name": "Taegis XDR",
                "config": "",
                "params": {
                  "investigation_id": "",
                  "events": ""
                },
                "version": "1.2.0",
                "connector": "taegis-xdr",
                "operation": "add_events_to_investigation",
                "operationTitle": "Add Events to Investigation"
              },
              "left": "188",
              "top": "120",
              "stepType": "/api/3/workflow_step_types/0bfed618-0316-11e7-93ae-92361f002671"
            }
          ],
          "triggerLimit": null,
          "description": "Adds Events to an existing investigation based on the investigation ID.",
          "name": "Add Events to Investigation",
          "tag": "#Taegis XDR",
          "recordTags": [
            "Taegis",
            "taegis-xdr"
          ],
          "isActive": false,
          "debug": false,
          "singleRecordExecution": false,
          "parameters": [],
          "synchronous": false,
          "triggerStep": "/api/3/workflow_steps/653f6283-63d6-42a8-9c2f-4bdc91599645",
          "routes": [
            {
              "uuid": "bfcefb79-7595-4019-ae2a-16c11904fcfb",
              "@type": "WorkflowRoute",
              "label": null,
              "isExecuted": false,
              "name": "Start-> Add Events to Investigation",
              "sourceStep": "/api/3/workflow_steps/653f6283-63d6-42a8-9c2f-4bdc91599645",
              "targetStep": "/api/3/workflow_steps/775de46f-c4a7-475f-9769-bf3fa1d34177"
            }
          ]
        },
        {
          "@type": "Workflow",
          "uuid": "577de0bf-49e5-454c-8a93-cb985261bdd9",
          "collection": "/api/3/workflow_collections/3586dab8-5e82-4b17-ab27-aa236138a1ef",
          "steps": [
            {
              "uuid": "22eca4f8-d1ca-4966-9618-367d9e19f51f",
              "@type": "WorkflowStep",
              "name": "Start",
              "description": null,
              "status": null,
              "arguments": {
                "step_variables": {
                  "input": {
                    "params": []
                  }
                }
              },
              "left": "20",
              "top": "20",
              "stepType": "/api/3/workflow_step_types/b348f017-9a94-471f-87f8-ce88b6a7ad62"
            },
            {
              "uuid": "fe3360ff-67a4-472c-afca-1f1ed9acb358",
              "@type": "WorkflowStep",
              "name": "Create Comment",
              "description": null,
              "status": null,
              "arguments": {
                "name": "Taegis XDR",
                "config": "",
                "params": {
                  "investigationId": "",
                  "comment": ""
                },
                "version": "1.2.0",
                "connector": "taegis-xdr",
                "operation": "create_comment",
                "operationTitle": "Create Comment"
              },
              "left": "188",
              "top": "120",
              "stepType": "/api/3/workflow_step_types/0bfed618-0316-11e7-93ae-92361f002671"
            }
          ],
          "triggerLimit": null,
          "description": "Create a new comment in the activity log for investigation.",
          "name": "Create Comment",
          "tag": "#Taegis XDR",
          "recordTags": [
            "Taegis",
            "taegis-xdr"
          ],
          "isActive": false,
          "debug": false,
          "singleRecordExecution": false,
          "parameters": [],
          "synchronous": false,
          "triggerStep": "/api/3/workflow_steps/22eca4f8-d1ca-4966-9618-367d9e19f51f",
          "routes": [
            {
              "uuid": "5ea49534-51bb-4c9f-abd8-6c9ad77a42ee",
              "@type": "WorkflowRoute",
              "label": null,
              "isExecuted": false,
              "name": "Start-> Create Comment",
              "sourceStep": "/api/3/workflow_steps/22eca4f8-d1ca-4966-9618-367d9e19f51f",
              "targetStep": "/api/3/workflow_steps/fe3360ff-67a4-472c-afca-1f1ed9acb358"
            }
          ]
        },
        {
          "@type": "Workflow",
          "uuid": "50eba367-e9f9-40b6-b511-cda95e566fed",
          "collection": "/api/3/workflow_collections/3586dab8-5e82-4b17-ab27-aa236138a1ef",
          "steps": [
            {
              "uuid": "76da2ac8-64ad-4cfa-b40d-e2da78a2fd59",
              "@type": "WorkflowStep",
              "name": "Start",
              "description": null,
              "status": null,
              "arguments": {
                "step_variables": {
                  "input": {
                    "params": []
                  }
                }
              },
              "left": "20",
              "top": "20",
              "stepType": "/api/3/workflow_step_types/b348f017-9a94-471f-87f8-ce88b6a7ad62"
            },
            {
              "uuid": "f4865af0-45d9-441c-af91-08ac59edfe70",
              "@type": "WorkflowStep",
              "name": "Get Alerts",
              "description": null,
              "status": null,
              "arguments": {
                "name": "Taegis XDR",
                "config": "",
                "params": {
                  "cql_query": "FROM alert WHERE severity >= 0.6 AND status = 'OPEN' EARLIEST=-1d",
                  "limit": 10,
                  "offset": ""
                },
                "version": "1.2.0",
                "connector": "taegis-xdr",
                "operation": "get_alerts",
                "operationTitle": "Get Alerts"
              },
              "left": "188",
              "top": "120",
              "stepType": "/api/3/workflow_step_types/0bfed618-0316-11e7-93ae-92361f002671"
            }
          ],
          "triggerLimit": null,
          "description": "Retrieves all alerts with Common Fields of Interests based on the filter query and other input parameters specified.",
          "name": "Get Alerts",
          "tag": "#Taegis XDR",
          "recordTags": [
            "Taegis",
            "taegis-xdr"
          ],
          "isActive": false,
          "debug": false,
          "singleRecordExecution": false,
          "parameters": [],
          "synchronous": false,
          "triggerStep": "/api/3/workflow_steps/76da2ac8-64ad-4cfa-b40d-e2da78a2fd59",
          "routes": [
            {
              "uuid": "f53097a5-d8d7-4a98-8583-9d907ff781d9",
              "@type": "WorkflowRoute",
              "label": null,
              "isExecuted": false,
              "name": "Start-> Get Alerts",
              "sourceStep": "/api/3/workflow_steps/76da2ac8-64ad-4cfa-b40d-e2da78a2fd59",
              "targetStep": "/api/3/workflow_steps/f4865af0-45d9-441c-af91-08ac59edfe70"
            }
          ]
        },
        {
          "@type": "Workflow",
          "uuid": "64b5ab0a-3253-4739-b925-575242958c5e",
          "collection": "/api/3/workflow_collections/3586dab8-5e82-4b17-ab27-aa236138a1ef",
          "steps": [
            {
              "uuid": "ae09710c-e938-42d4-931e-41c3fff320ee",
              "@type": "WorkflowStep",
              "name": "Start",
              "description": null,
              "status": null,
              "arguments": {
                "step_variables": {
                  "input": {
                    "params": []
                  }
                }
              },
              "left": "20",
              "top": "20",
              "stepType": "/api/3/workflow_step_types/b348f017-9a94-471f-87f8-ce88b6a7ad62"
            },
            {
              "uuid": "e2b3fd05-7dd9-4caf-add4-c3432429a75b",
              "@type": "WorkflowStep",
              "name": "Update Alert Status",
              "description": null,
              "status": null,
              "arguments": {
                "name": "Taegis XDR",
                "config": "",
                "params": {
                  "alert_ids": "",
                  "resolution_status": "False Positive",
                  "reason": ""
                },
                "version": "1.2.0",
                "connector": "taegis-xdr",
                "operation": "update_alert_status",
                "operationTitle": "Update Alert Status"
              },
              "left": "188",
              "top": "120",
              "stepType": "/api/3/workflow_step_types/0bfed618-0316-11e7-93ae-92361f002671"
            }
          ],
          "triggerLimit": null,
          "description": "Adds a resolution status or modifies an existing resolution status based on the alert IDs and other input parameters specified.",
          "name": "Update Alert Status",
          "tag": "#Taegis XDR",
          "recordTags": [
            "Taegis",
            "taegis-xdr"
          ],
          "isActive": false,
          "debug": false,
          "singleRecordExecution": false,
          "parameters": [],
          "synchronous": false,
          "triggerStep": "/api/3/workflow_steps/ae09710c-e938-42d4-931e-41c3fff320ee",
          "routes": [
            {
              "uuid": "e9c29a33-e603-465b-9e18-bf014969bbc2",
              "@type": "WorkflowRoute",
              "label": null,
              "isExecuted": false,
              "name": "Start-> Update Alert Status",
              "sourceStep": "/api/3/workflow_steps/ae09710c-e938-42d4-931e-41c3fff320ee",
              "targetStep": "/api/3/workflow_steps/e2b3fd05-7dd9-4caf-add4-c3432429a75b"
            }
          ]
        },
        {
          "@type": "Workflow",
          "uuid": "fdb14984-1d16-4770-8eb6-3c979de7719e",
          "collection": "/api/3/workflow_collections/3586dab8-5e82-4b17-ab27-aa236138a1ef",
          "steps": [
            {
              "uuid": "e5bac225-7e7f-462a-b057-2e6e2299aa83",
              "@type": "WorkflowStep",
              "name": "Start",
              "description": null,
              "status": null,
              "arguments": {
                "step_variables": {
                  "input": {
                    "params": []
                  }
                }
              },
              "left": "20",
              "top": "20",
              "stepType": "/api/3/workflow_step_types/b348f017-9a94-471f-87f8-ce88b6a7ad62"
            },
            {
              "uuid": "06722616-3e19-4d10-b0de-5f101a399fe8",
              "@type": "WorkflowStep",
              "name": "Get Assets",
              "description": null,
              "status": null,
              "arguments": {
                "name": "Taegis XDR",
                "config": "",
                "params": {
                  "filter_asset_state": "All",
                  "order_by": "Hostname",
                  "orderDirection": "Ascending",
                  "only_most_recent": "",
                  "limit": 10,
                  "offset": ""
                },
                "version": "1.2.0",
                "connector": "taegis-xdr",
                "operation": "get_assets",
                "operationTitle": "Get Assets"
              },
              "left": "188",
              "top": "120",
              "stepType": "/api/3/workflow_step_types/0bfed618-0316-11e7-93ae-92361f002671"
            }
          ],
          "triggerLimit": null,
          "description": "Retrieves a list of assets based on the filter asset state, order, and other input parameters specified.",
          "name": "Get Assets",
          "tag": "#Taegis XDR",
          "recordTags": [
            "Taegis",
            "taegis-xdr"
          ],
          "isActive": false,
          "debug": false,
          "singleRecordExecution": false,
          "parameters": [],
          "synchronous": false,
          "triggerStep": "/api/3/workflow_steps/e5bac225-7e7f-462a-b057-2e6e2299aa83",
          "routes": [
            {
              "uuid": "2e63d7b3-206b-4340-bb51-b2c44b6c49d8",
              "@type": "WorkflowRoute",
              "label": null,
              "isExecuted": false,
              "name": "Start-> Get Assets",
              "sourceStep": "/api/3/workflow_steps/e5bac225-7e7f-462a-b057-2e6e2299aa83",
              "targetStep": "/api/3/workflow_steps/06722616-3e19-4d10-b0de-5f101a399fe8"
            }
          ]
        },
        {
          "@type": "Workflow",
          "uuid": "80ef4295-46e3-4da4-9788-7379a0a9452b",
          "collection": "/api/3/workflow_collections/3586dab8-5e82-4b17-ab27-aa236138a1ef",
          "steps": [
            {
              "uuid": "b129b9dd-919d-47c9-bcdb-3edea77f3c9b",
              "@type": "WorkflowStep",
              "name": "Start",
              "description": null,
              "status": null,
              "arguments": {
                "step_variables": {
                  "input": {
                    "params": []
                  }
                }
              },
              "left": "20",
              "top": "20",
              "stepType": "/api/3/workflow_step_types/b348f017-9a94-471f-87f8-ce88b6a7ad62"
            },
            {
              "uuid": "2514a2ad-1b9d-4b7b-ad89-fc82175979fa",
              "@type": "WorkflowStep",
              "name": "Isolate Assets",
              "description": null,
              "status": null,
              "arguments": {
                "name": "Taegis XDR",
                "config": "",
                "params": {
                  "id": "",
                  "reason": ""
                },
                "version": "1.2.0",
                "connector": "taegis-xdr",
                "operation": "isolate_assets",
                "operationTitle": "Isolate Assets"
              },
              "left": "188",
              "top": "120",
              "stepType": "/api/3/workflow_step_types/0bfed618-0316-11e7-93ae-92361f002671"
            }
          ],
          "triggerLimit": null,
          "description": "Isolates the asset based on the Asset ID and the isolation reason specified.",
          "name": "Isolate Assets",
          "tag": "#Taegis XDR",
          "recordTags": [
            "Taegis",
            "taegis-xdr"
          ],
          "isActive": false,
          "debug": false,
          "singleRecordExecution": false,
          "parameters": [],
          "synchronous": false,
          "triggerStep": "/api/3/workflow_steps/b129b9dd-919d-47c9-bcdb-3edea77f3c9b",
          "routes": [
            {
              "uuid": "59a69db4-d890-44e8-a9f2-f8f40abbcd0c",
              "@type": "WorkflowRoute",
              "label": null,
              "isExecuted": false,
              "name": "Start-> Isolate Assets",
              "sourceStep": "/api/3/workflow_steps/b129b9dd-919d-47c9-bcdb-3edea77f3c9b",
              "targetStep": "/api/3/workflow_steps/2514a2ad-1b9d-4b7b-ad89-fc82175979fa"
            }
          ]
        },
        {
          "@type": "Workflow",
          "uuid": "03e3066d-3aec-4407-802a-ad0987fc01bf",
          "collection": "/api/3/workflow_collections/3586dab8-5e82-4b17-ab27-aa236138a1ef",
          "steps": [
            {
              "uuid": "b7c9334d-e1c5-49b3-99d7-3206c8bb3ea2",
              "@type": "WorkflowStep",
              "name": "Start",
              "description": null,
              "status": null,
              "arguments": {
                "step_variables": {
                  "input": {
                    "params": []
                  }
                }
              },
              "left": "20",
              "top": "20",
              "stepType": "/api/3/workflow_step_types/b348f017-9a94-471f-87f8-ce88b6a7ad62"
            },
            {
              "uuid": "785baf56-6176-4c5e-b63b-f7fac52f6b3d",
              "@type": "WorkflowStep",
              "name": "Get User by ID",
              "description": null,
              "status": null,
              "arguments": {
                "name": "Taegis XDR",
                "config": "",
                "params": {
                  "id": "",
                  "tenant_id": ""
                },
                "version": "1.2.0",
                "connector": "taegis-xdr",
                "operation": "get_user_by_id",
                "operationTitle": "Get User by ID"
              },
              "left": "188",
              "top": "120",
              "stepType": "/api/3/workflow_step_types/0bfed618-0316-11e7-93ae-92361f002671"
            }
          ],
          "triggerLimit": null,
          "description": "Retrieves the state of a playbook execution based on the user and tenant ID specified.",
          "name": "Get User by ID",
          "tag": "#Taegis XDR",
          "recordTags": [
            "Taegis",
            "taegis-xdr"
          ],
          "isActive": false,
          "debug": false,
          "singleRecordExecution": false,
          "parameters": [],
          "synchronous": false,
          "triggerStep": "/api/3/workflow_steps/b7c9334d-e1c5-49b3-99d7-3206c8bb3ea2",
          "routes": [
            {
              "uuid": "31a9b47c-e384-4935-9b52-99e1b099e6a5",
              "@type": "WorkflowRoute",
              "label": null,
              "isExecuted": false,
              "name": "Start-> Get User by ID",
              "sourceStep": "/api/3/workflow_steps/b7c9334d-e1c5-49b3-99d7-3206c8bb3ea2",
              "targetStep": "/api/3/workflow_steps/785baf56-6176-4c5e-b63b-f7fac52f6b3d"
            }
          ]
        },
        {
          "@type": "Workflow",
          "uuid": "00f39203-4ba5-4fa6-95dd-9f9442be08c4",
          "collection": "/api/3/workflow_collections/3586dab8-5e82-4b17-ab27-aa236138a1ef",
          "steps": [
            {
              "uuid": "2cb64368-5b5d-4f4f-be69-b0656e1b29f4",
              "@type": "WorkflowStep",
              "name": "Start",
              "description": null,
              "status": null,
              "arguments": {
                "step_variables": {
                  "input": {
                    "params": []
                  }
                }
              },
              "left": "20",
              "top": "20",
              "stepType": "/api/3/workflow_step_types/b348f017-9a94-471f-87f8-ce88b6a7ad62"
            },
            {
              "uuid": "4025999b-d204-42be-865c-90d27165058d",
              "@type": "WorkflowStep",
              "name": "Get Endpoint",
              "description": null,
              "status": null,
              "arguments": {
                "name": "Taegis XDR",
                "config": "",
                "params": {
                  "id": ""
                },
                "version": "1.2.0",
                "connector": "taegis-xdr",
                "operation": "get_endpoint",
                "operationTitle": "Get Endpoint"
              },
              "left": "188",
              "top": "120",
              "stepType": "/api/3/workflow_step_types/0bfed618-0316-11e7-93ae-92361f002671"
            }
          ],
          "triggerLimit": null,
          "description": "Retrieves a RedCloak endpoint info based on the endpoint ID specified.",
          "name": "Get Endpoint",
          "tag": "#Taegis XDR",
          "recordTags": [
            "Taegis",
            "taegis-xdr"
          ],
          "isActive": false,
          "debug": false,
          "singleRecordExecution": false,
          "parameters": [],
          "synchronous": false,
          "triggerStep": "/api/3/workflow_steps/2cb64368-5b5d-4f4f-be69-b0656e1b29f4",
          "routes": [
            {
              "uuid": "55d3dabc-fbb3-4a31-841e-c7d4aaaf32b4",
              "@type": "WorkflowRoute",
              "label": null,
              "isExecuted": false,
              "name": "Start-> Get Endpoint",
              "sourceStep": "/api/3/workflow_steps/2cb64368-5b5d-4f4f-be69-b0656e1b29f4",
              "targetStep": "/api/3/workflow_steps/4025999b-d204-42be-865c-90d27165058d"
            }
          ]
        },
        {
          "@type": "Workflow",
          "uuid": "3f4f9210-1554-4497-86a2-4e1006713fa4",
          "collection": "/api/3/workflow_collections/3586dab8-5e82-4b17-ab27-aa236138a1ef",
          "steps": [
            {
              "uuid": "6bb91c06-afda-4361-9ee9-ce5bbb3acf5e",
              "@type": "WorkflowStep",
              "name": "Start",
              "description": null,
              "status": null,
              "arguments": {
                "step_variables": {
                  "input": {
                    "params": []
                  }
                }
              },
              "left": "20",
              "top": "20",
              "stepType": "/api/3/workflow_step_types/b348f017-9a94-471f-87f8-ce88b6a7ad62"
            },
            {
              "uuid": "7e32e0be-6c99-4487-950e-b916a9407a56",
              "@type": "WorkflowStep",
              "name": "Get Playbook Execution",
              "description": null,
              "status": null,
              "arguments": {
                "name": "Taegis XDR",
                "config": "",
                "params": {
                  "playbookExecutionId": ""
                },
                "version": "1.2.0",
                "connector": "taegis-xdr",
                "operation": "get_playbook_execution",
                "operationTitle": "Get Playbook Execution"
              },
              "left": "188",
              "top": "120",
              "stepType": "/api/3/workflow_step_types/0bfed618-0316-11e7-93ae-92361f002671"
            }
          ],
          "triggerLimit": null,
          "description": "Retrieves the state of a playbook execution based on the playbook execution ID specified.",
          "name": "Get Playbook Execution",
          "tag": "#Taegis XDR",
          "recordTags": [
            "Taegis",
            "taegis-xdr"
          ],
          "isActive": false,
          "debug": false,
          "singleRecordExecution": false,
          "parameters": [],
          "synchronous": false,
          "triggerStep": "/api/3/workflow_steps/6bb91c06-afda-4361-9ee9-ce5bbb3acf5e",
          "routes": [
            {
              "uuid": "f42553a5-0897-4579-bc75-cf65f7abafd2",
              "@type": "WorkflowRoute",
              "label": null,
              "isExecuted": false,
              "name": "Start-> Get Playbook Execution",
              "sourceStep": "/api/3/workflow_steps/6bb91c06-afda-4361-9ee9-ce5bbb3acf5e",
              "targetStep": "/api/3/workflow_steps/7e32e0be-6c99-4487-950e-b916a9407a56"
            }
          ]
        },
        {
          "@type": "Workflow",
          "uuid": "ab12af11-7e17-4683-82c0-491f502c75fe",
          "collection": "/api/3/workflow_collections/3586dab8-5e82-4b17-ab27-aa236138a1ef",
          "steps": [
            {
              "uuid": "0642f04b-dcfb-4065-aac6-84e2cdcb85a6",
              "@type": "WorkflowStep",
              "name": "Start",
              "description": null,
              "status": null,
              "arguments": {
                "step_variables": {
                  "input": {
                    "params": []
                  }
                }
              },
              "left": "20",
              "top": "20",
              "stepType": "/api/3/workflow_step_types/b348f017-9a94-471f-87f8-ce88b6a7ad62"
            },
            {
              "uuid": "83db59e3-15a5-415f-8ccf-fba5a252523b",
              "@type": "WorkflowStep",
              "name": "Execute Playbook",
              "description": null,
              "status": null,
              "arguments": {
                "name": "Taegis XDR",
                "config": "",
                "params": {
                  "playbookInstanceId": "",
                  "parameters": ""
                },
                "version": "1.2.0",
                "connector": "taegis-xdr",
                "operation": "execute_playbook",
                "operationTitle": "Execute Playbook"
              },
              "left": "188",
              "top": "120",
              "stepType": "/api/3/workflow_step_types/0bfed618-0316-11e7-93ae-92361f002671"
            }
          ],
          "triggerLimit": null,
          "description": "Execute playbook instance in Taegis XDR system according to Playbook ID and supplied parameters.",
          "name": "Execute Playbook",
          "tag": "#Taegis XDR",
          "recordTags": [
            "Taegis",
            "taegis-xdr"
          ],
          "isActive": false,
          "debug": false,
          "singleRecordExecution": false,
          "parameters": [],
          "synchronous": false,
          "triggerStep": "/api/3/workflow_steps/0642f04b-dcfb-4065-aac6-84e2cdcb85a6",
          "routes": [
            {
              "uuid": "25fcaecf-4aa5-477b-ad7c-45b8c6c3b197",
              "@type": "WorkflowRoute",
              "label": null,
              "isExecuted": false,
              "name": "Start-> Execute Playbook",
              "sourceStep": "/api/3/workflow_steps/0642f04b-dcfb-4065-aac6-84e2cdcb85a6",
              "targetStep": "/api/3/workflow_steps/83db59e3-15a5-415f-8ccf-fba5a252523b"
            }
          ]
        }
      ],
      "name": "Sample - Taegis XDR - 1.2.0",
      "description": "SecureWorks Taegis\u2122 XDR offers superior detection, unmatched response and an open platform built from the ground up to integrate market-leading technologies and deliver the highest ROI.",
      "visible": true,
      "recordTags": [
        "Taegis",
        "taegis-xdr"
      ]
    }
  ]
}